lektor_image_resize.py
lektor_image_resize-1.0.0.dist-info/LICENSE
lektor_image_resize-1.0.0.dist-info/METADATA
lektor_image_resize-1.0.0.dist-info/WHEEL
lektor_image_resize-1.0.0.dist-info/entry_points.txt
lektor_image_resize-1.0.0.dist-info/top_level.txt
lektor_image_resize-1.0.0.dist-info/RECORD
