Metadata-Version: 2.1
Name: lektor-image-resize
Version: 1.0.0
Summary: Generate JPG and WEBP Images and Thumbnails in predefined sizes.
Home-page: https://github.com/chaos-bodensee/lektor-image-resize.git
Author: L3D
Author-email: l3d@c3woc.de
License: MIT
Keywords: Lektor plugin generate webp jpg thumbnails images
Platform: UNKNOWN
Classifier: Framework :: Lektor
Classifier: Environment :: Plugins
License-File: LICENSE
